simple_image_download/__init__.py
simple_image_download/simple_image_download.py
simple_image_download-0.5.dist-info/LICENSE.txt
simple_image_download-0.5.dist-info/METADATA
simple_image_download-0.5.dist-info/WHEEL
simple_image_download-0.5.dist-info/top_level.txt
simple_image_download-0.5.dist-info/RECORD
