Metadata-Version: 2.1
Name: simple-image-download
Version: 0.5
Summary: Downloads raw page from google images and searches for images that can be downloaded
Home-page: https://github.com/RiddlerQ/simple_image_download
Download-URL: https://pypi.org/project/simple_image_download/
Author: Jakub Dobies
Author-email: kuba.dobies@onet.pl
License: MIT
Keywords: google images,image downloader
Platform: UNKNOWN
License-File: LICENSE.txt
